LICENSE
README.md
setup.py
cd_fvd.egg-info/PKG-INFO
cd_fvd.egg-info/SOURCES.txt
cd_fvd.egg-info/dependency_links.txt
cd_fvd.egg-info/requires.txt
cd_fvd.egg-info/top_level.txt
cdfvd/__init__.py
cdfvd/fvd.py
cdfvd/third_party/__init__.py
cdfvd/third_party/VideoMAEv2/__init__.py
cdfvd/third_party/VideoMAEv2/utils.py
cdfvd/third_party/VideoMAEv2/videomaev2_finetune.py
cdfvd/third_party/VideoMAEv2/videomaev2_pretrain.py
cdfvd/third_party/i3d/__init__.py
cdfvd/third_party/i3d/pytorch_i3d.py
cdfvd/third_party/i3d/utils.py
cdfvd/utils/__init__.py
cdfvd/utils/data_utils.py
cdfvd/utils/metric_utils.py