Metadata-Version: 2.1
Name: cd-fvd
Version: 0.1.1
Summary: FVD calculation in PyTorch with I3D or VideoMAE models
Home-page: https://github.com/songweige/content-debiased-fvd
Author: Songwei Ge
Author-email: songweig@cs.umd.edu
Classifier: Programming Language :: Python :: 3
Classifier: License :: OSI Approved :: BSD License
Classifier: Operating System :: OS Independent
License-File: LICENSE
